pyautoplot/__init__.py
pyautoplot-1.0.2.dist-info/licenses/LICENSE
pyautoplot-1.0.2.dist-info/METADATA
pyautoplot-1.0.2.dist-info/WHEEL
pyautoplot-1.0.2.dist-info/top_level.txt
pyautoplot-1.0.2.dist-info/RECORD
